hh_polygons/__init__.py
hh_polygons/__main__.py
hh_polygons/polygons.py
hh_polygons/server.py
hh_polygons/sql.py
hh_polygons/util.py
hh_polygons-0.0.18.dist-info/LICENSE
hh_polygons-0.0.18.dist-info/METADATA
hh_polygons-0.0.18.dist-info/WHEEL
hh_polygons-0.0.18.dist-info/top_level.txt
hh_polygons-0.0.18.dist-info/RECORD
