Metadata-Version: 2.1
Name: hh-polygons
Version: 0.0.18
Summary: HafrenHaver Support Services
License-File: LICENSE
Requires-Dist: flask
Requires-Dist: joblib
Requires-Dist: peval
Requires-Dist: psycopg2
Requires-Dist: shapely
Requires-Dist: sympy
Requires-Dist: teamhack-db
Provides-Extra: rel
Requires-Dist: twine ; extra == 'rel'
Provides-Extra: test
Requires-Dist: coverage ; extra == 'test'
Requires-Dist: pytest ; extra == 'test'
